brostel/__init__.py
brostel/api.py
brostel/config/__init__.py
brostel/config/manager.py
brostel/config/settings.py
brostel/core/__init__.py
brostel/core/builder.py
brostel/core/message.py
brostel/formatters/__init__.py
brostel/formatters/tags.py
brostel/formatters/text.py
brostel/misc/__init__.py
brostel/parsers/__init__.py
brostel/parsers/buttons.py
brostel/parsers/tags.py
brostel/types/__init__.py
brostel/types/message.py
brostel/utils/__init__.py
brostel/utils/entities.py
brostel/utils/validation.py
brostel-1.0.1.dist-info/licenses/LICENSE
brostel-1.0.1.dist-info/METADATA
brostel-1.0.1.dist-info/WHEEL
brostel-1.0.1.dist-info/top_level.txt
brostel-1.0.1.dist-info/RECORD
