Metadata-Version: 2.4
Name: brostel
Version: 1.0.1
Summary: Telegram formatting tool for telegrinder
Author-email: ventuero <amerfoe@gmail.com>
Maintainer-email: ventuero <amerfoe@gmail.com>
Project-URL: Homepage, https://github.com/ventuero/brostel/
Project-URL: Repository, https://github.com/ventuero/brostel
Project-URL: Bug Tracker, https://github.com/ventuero/brostel/issues
Keywords: async,asyncio,text,fmt,format,formatting,telegram,bot,telegrinder,html,entities
Classifier: Development Status :: 5 - Production/Stable
Classifier: Intended Audience :: Developers
Classifier: License :: OSI Approved :: MIT License
Classifier: Operating System :: OS Independent
Classifier: Programming Language :: Python :: 3
Classifier: Programming Language :: Python :: 3.13
Classifier: Programming Language :: Python :: 3 :: Only
Classifier: Topic :: Communications :: Chat
Classifier: Topic :: Internet
Classifier: Topic :: Software Development :: Libraries :: Python Modules
Classifier: Topic :: Text Processing :: Markup :: HTML
Classifier: Framework :: AsyncIO
Classifier: Typing :: Typed
Requires-Python: >=3.13
License-File: LICENSE
Requires-Dist: markupsafe<4.0.0,>=3.0.2
Requires-Dist: sulguk<1.0.0,>=0.9.1
Provides-Extra: dev
Requires-Dist: ruff>=0.13.0; extra == "dev"
Requires-Dist: telegrinder; extra == "dev"
Dynamic: license-file
